rapideye/__init__.py
rapideye-0.1.4.dist-info/DESCRIPTION.rst
rapideye-0.1.4.dist-info/METADATA
rapideye-0.1.4.dist-info/RECORD
rapideye-0.1.4.dist-info/WHEEL
rapideye-0.1.4.dist-info/entry_points.txt
rapideye-0.1.4.dist-info/metadata.json
rapideye-0.1.4.dist-info/top_level.txt
