Metadata-Version: 2.0
Name: rapideye
Version: 0.1.4
Summary: An Image Search Toolkit based on OpenCV.
Home-page: https://github.com/mertyildiran/RapidEye
Author: Mehmet Mert Yildiran
Author-email: mert.yildiran@bil.omu.edu.tr
License: MIT
Keywords: image search histogram comparison
Platform: UNKNOWN
Classifier: Development Status :: 3 - Alpha
Classifier: Intended Audience :: Developers
Classifier: Topic :: Scientific/Engineering :: Image Recognition
Classifier: License :: OSI Approved :: MIT License
Classifier: Programming Language :: Python :: 2.7
